fastapi_server_session/__init__.py
fastapi_server_session/manager.py
fastapi_server_session/session.py
fastapi_server_session/interfaces/base.py
fastapi_server_session/interfaces/redis.py
fastapi_server_session-0.0.1.dist-info/METADATA
fastapi_server_session-0.0.1.dist-info/WHEEL
fastapi_server_session-0.0.1.dist-info/top_level.txt
fastapi_server_session-0.0.1.dist-info/RECORD
