Metadata-Version: 2.1
Name: fastapi-server-session
Version: 0.0.1
Summary: A dependency-based extension for FastAPI that adds support for server-sided session management
Home-page: https://github.com/ahnaf-zamil/fastapi-server-session
Author: DevGuyAhnaf
Author-email: ahnaf@ahnafzamil.com
License: MIT
Platform: UNKNOWN
Classifier: License :: OSI Approved :: MIT License
Classifier: Operating System :: OS Independent
Classifier: Programming Language :: Python :: 3.6
Requires-Python: >=3.6
Requires-Dist: fastapi
Requires-Dist: redis
